setup.py
ThreatPlaybook_Client.egg-info/PKG-INFO
ThreatPlaybook_Client.egg-info/SOURCES.txt
ThreatPlaybook_Client.egg-info/dependency_links.txt
ThreatPlaybook_Client.egg-info/entry_points.txt
ThreatPlaybook_Client.egg-info/requires.txt
ThreatPlaybook_Client.egg-info/top_level.txt
playbook/__init__.py
playbook/playbook.py
playbook/utils.py