Metadata-Version: 1.0
Name: ThreatPlaybook-Client
Version: 3.1
Summary: Client for ThreatPlaybook that allows a user to interacts with the ThreatPlaybook API
Home-page: https://we45.github.io/threatplaybook/
Author: we45
Author-email: info@we45.com
License: MIT License
Platform: UNKNOWN
